data_team_py_slack_notifier/__init__.py
data_team_py_slack_notifier/data_team_py_slack_notifier.py
py_slack_notifier_chip_data_team-1.0.3.dist-info/LICENSE
py_slack_notifier_chip_data_team-1.0.3.dist-info/METADATA
py_slack_notifier_chip_data_team-1.0.3.dist-info/WHEEL
py_slack_notifier_chip_data_team-1.0.3.dist-info/top_level.txt
py_slack_notifier_chip_data_team-1.0.3.dist-info/RECORD
