Metadata-Version: 2.1
Name: py-slack-notifier-chip-data-team
Version: 1.0.3
Summary: Processes notifications from SNS or custom and sends them to slack.     
Home-page: UNKNOWN
Author: Bernard Louis Alecu
Author-email: louis.alecu@getchip.uk
License: LICENSE
Platform: UNKNOWN
Requires-Python: >=3.8
License-File: LICENSE
Requires-Dist: pytest
Requires-Dist: slack-sdk
Requires-Dist: twine
Requires-Dist: wheel
